rtl/matrix.v
module matrix (state,res);
  input [15:0]state;
  output [15:0]res;
  
  assign res={state[11:8]^state[7:4]^state[3:0],state[15:12]^state[7:4]^state[3:0],state[15:12]^state[11:8]^state[3:0],state[15:12]^state[11:8]^state[7:4]};
endmodule

rtl/sbox.v

module sbox(s_in,s_out);
	input [3:0]s_in;
	output reg [3:0] s_out;
	
	always @(s_in)
		case(s_in)
			4'd0: s_out = 4'd0;
			4'd1: s_out = 4'd15;
			4'd2: s_out = 4'd14;
			4'd3: s_out = 4'd5;
			4'd4: s_out = 4'd13;
			4'd5: s_out = 4'd3;
			4'd6: s_out = 4'd6;
			4'd7: s_out = 4'd12;
			4'd8: s_out = 4'd11;
			4'd9: s_out = 4'd9;
			4'd10: s_out = 4'd10;
			4'd11: s_out = 4'd8;
			4'd12: s_out = 4'd7;
			4'd13: s_out = 4'd4;
			4'd14: s_out = 4'd2;
			4'd15: s_out = 4'd1;
		endcase
	
endmodule

rtl/SubNibble.v
module SubNibble(s_in,s_out1);
	input [63:0]s_in;
	output [63:0]s_out1;

                wire [63:0]s_out,s_out1;

	sbox s1(s_in[3:0],s_out[3:0]);
	sbox s2(s_in[7:4],s_out[7:4]);
	sbox s3(s_in[11:8],s_out[11:8]);
	sbox s4(s_in[15:12],s_out[15:12]);
	sbox s5(s_in[19:16],s_out[19:16]);
	sbox s6(s_in[23:20],s_out[23:20]);
	sbox s7(s_in[27:24],s_out[27:24]);
	sbox s8(s_in[31:28],s_out[31:28]);
	sbox s9(s_in[35:32],s_out[35:32]);
	sbox s10(s_in[39:36],s_out[39:36]);
	sbox s11(s_in[43:40],s_out[43:40]);
	sbox s12(s_in[47:44],s_out[47:44]);
	sbox s13(s_in[51:48],s_out[51:48]);
	sbox s14(s_in[55:52],s_out[55:52]);
	sbox s15(s_in[59:56],s_out[59:56]);
	sbox s16(s_in[63:60],s_out[63:60]);

assign s_out1={s_out[63:60],s_out[35:32],s_out[23:20],s_out[11:8],s_out[47:44],s_out[19:16],s_out[7:4],s_out[59:56],s_out[31:28],s_out[3:0],s_out[55:52],s_out[43:40],s_out[15:12],s_out[51:48],s_out[39:36],s_out[27:24]};
endmodule

rtl/keyex.v
module keyex(key,cnt,r_key);
  input[79:0]key;
  input[4:0]cnt; 
  output[79:0]r_key;

 wire  [3:0] rk;
 sbox  sk(key[3:0],rk[3:0]);
 assign r_key={key[39:35]^cnt,key[34:4],rk[3:0],key[68:40],key[79:69]};

endmodule

rtl/IVLBC.v
module IVLBC(input [63:0] state,     // PlainText
             input [79:0] keys,      // key
             input sys_clk,          // clock
             input encrypt_start,    // start encrypt
             output reg encrypt_end, // encrypt finish
             output [63:0] result);  // final result

reg   [4:0] cnt;
reg   [63:0]  res;
reg   [79:0]  k;
wire  [63:0]  te,te1,s_add;
wire  [79:0]  r_keys;



always @(posedge sys_clk)  begin
    cnt <= (encrypt_start)? cnt+1: 1;
    res <= ((encrypt_start) ?te:state) ;
    k   <= ((encrypt_start) ?r_keys:keys) ;
    if (cnt == 29) begin
        res <= res;
        end else begin
        res <= ((encrypt_start) ?te:state) ;
    end
end

// end encrypt if encrypt finish by cnt
always @(posedge  sys_clk) begin
    if (cnt == 29 && encrypt_start) begin
        encrypt_end = 1;
    end
    else begin
        encrypt_end = 0;
    end
end

// round encrypt
keyex  kq(k,cnt,r_keys);
assign s_add = res ^ r_keys[79:16];
SubNibble   s1(s_add,te1);
matrix m1(te1[63:48],te[63:48]);
matrix m2(te1[47:32],te[47:32]);
matrix m3(te1[31:16],te[31:16]);
matrix m4(te1[15:0],te[15:0]);
assign result = res^k[79:16];

endmodule

rtl/tb_i.v
`timescale  1ns / 1ps

module tb_i();
    parameter PERIOD = 10;
    reg clk;
    reg rst_n;
    reg encrypt_start;
    reg [63:0] state;
    reg [79:0] keys;
    reg [23:0] counter;
    wire  encrypt_end;
    wire [63:0] result;     // small encode
    // generate colck
    initial begin
        rst_n         = 1'b1;
        clk           = 1'b0;
        encrypt_start = 1'b0;
        forever #(PERIOD/2)
            clk = ~clk;
        
    end
    
    initial begin
        state = 64'hffff_ffff_ffff_ffff;
        keys  = 80'hffff_ffff_ffff_ffff_ffff;
        #(PERIOD)
        encrypt_start = 1'b1;
    end
    
    
    always @(posedge clk) begin
        if (encrypt_end) begin
            encrypt_start <= 0;
        end
    end
    
    IVLBC u_i(
    .result(result),
    .state(state),
    .encrypt_start(encrypt_start),
    .encrypt_end(encrypt_end),
    .keys(keys),
    .sys_clk(clk));
    
    initial begin
        $dumpfile("./wave.vcd");
        $dumpvars(0, tb_i);
        #(PERIOD*40) $finish;
    end
    
endmodule

rtl/wave.vcd
$date
	Wed Mar 15 11:06:14 2023
$end
$version
	Icarus Verilog
$end
$timescale
	1ps
$end
$scope module tb_i $end
$var wire 64 ! result [63:0] $end
$var wire 1 " encrypt_end $end
$var parameter 32 # PERIOD $end
$var reg 1 $ clk $end
$var reg 1 % encrypt_start $end
$var reg 80 & keys [79:0] $end
$var reg 1 ' rst_n $end
$var reg 64 ( state [63:0] $end
$scope module u_i $end
$var wire 1 % encrypt_start $end
$var wire 80 ) keys [79:0] $end
$var wire 64 * result [63:0] $end
$var wire 64 + s_add [63:0] $end
$var wire 64 , state [63:0] $end
$var wire 1 $ sys_clk $end
$var wire 64 - te1 [63:0] $end
$var wire 64 . te [63:0] $end
$var wire 80 / r_keys [79:0] $end
$var reg 5 0 cnt [4:0] $end
$var reg 1 " encrypt_end $end
$var reg 80 1 k [79:0] $end
$var reg 64 2 res [63:0] $end
$scope module kq $end
$var wire 5 3 cnt [4:0] $end
$var wire 80 4 key [79:0] $end
$var wire 4 5 rk [3:0] $end
$var wire 80 6 r_key [79:0] $end
$scope module sk $end
$var wire 4 7 s_in [3:0] $end
$var reg 4 8 s_out [3:0] $end
$upscope $end
$upscope $end
$scope module m1 $end
$var wire 16 9 state [15:0] $end
$var wire 16 : res [15:0] $end
$upscope $end
$scope module m2 $end
$var wire 16 ; state [15:0] $end
$var wire 16 < res [15:0] $end
$upscope $end
$scope module m3 $end
$var wire 16 = state [15:0] $end
$var wire 16 > res [15:0] $end
$upscope $end
$scope module m4 $end
$var wire 16 ? state [15:0] $end
$var wire 16 @ res [15:0] $end
$upscope $end
$scope module s1 $end
$var wire 64 A s_in [63:0] $end
$var wire 64 B s_out1 [63:0] $end
$var wire 64 C s_out [63:0] $end
$scope module s1 $end
$var wire 4 D s_in [3:0] $end
$var reg 4 E s_out [3:0] $end
$upscope $end
$scope module s10 $end
$var wire 4 F s_in [3:0] $end
$var reg 4 G s_out [3:0] $end
$upscope $end
$scope module s11 $end
$var wire 4 H s_in [3:0] $end
$var reg 4 I s_out [3:0] $end
$upscope $end
$scope module s12 $end
$var wire 4 J s_in [3:0] $end
$var reg 4 K s_out [3:0] $end
$upscope $end
$scope module s13 $end
$var wire 4 L s_in [3:0] $end
$var reg 4 M s_out [3:0] $end
$upscope $end
$scope module s14 $end
$var wire 4 N s_in [3:0] $end
$var reg 4 O s_out [3:0] $end
$upscope $end
$scope module s15 $end
$var wire 4 P s_in [3:0] $end
$var reg 4 Q s_out [3:0] $end
$upscope $end
$scope module s16 $end
$var wire 4 R s_in [3:0] $end
$var reg 4 S s_out [3:0] $end
$upscope $end
$scope module s2 $end
$var wire 4 T s_in [3:0] $end
$var reg 4 U s_out [3:0] $end
$upscope $end
$scope module s3 $end
$var wire 4 V s_in [3:0] $end
$var reg 4 W s_out [3:0] $end
$upscope $end
$scope module s4 $end
$var wire 4 X s_in [3:0] $end
$var reg 4 Y s_out [3:0] $end
$upscope $end
$scope module s5 $end
$var wire 4 Z s_in [3:0] $end
$var reg 4 [ s_out [3:0] $end
$upscope $end
$scope module s6 $end
$var wire 4 \ s_in [3:0] $end
$var reg 4 ] s_out [3:0] $end
$upscope $end
$scope module s7 $end
$var wire 4 ^ s_in [3:0] $end
$var reg 4 _ s_out [3:0] $end
$upscope $end
$scope module s8 $end
$var wire 4 ` s_in [3:0] $end
$var reg 4 a s_out [3:0] $end
$upscope $end
$scope module s9 $end
$var wire 4 b s_in [3:0] $end
$var reg 4 c s_out [3:0] $end
$upscope $end
$upscope $end
$upscope $end
$upscope $end
$enddefinitions $end
$comment Show the parameter values. $end
$dumpall
b1010 #
$end
#0
$dumpvars
bx c
bx b
bx a
bx `
bx _
bx ^
bx ]
bx \
bx [
bx Z
bx Y
bx X
bx W
bx V
bx U
bx T
bx S
bx R
bx Q
bx P
bx O
bx N
bx M
bx L
bx K
bx J
bx I
bx H
bx G
bx F
bx E
bx D
bx C
bx B
bx A
bx @
bx ?
bx >
bx =
bx <
bx ;
bx :
bx 9
bx 8
bx 7
bx 6
bx 5
bx 4
bx 3
bx 2
bx 1
bx 0
bx /
bx .
bx -
b1111111111111111111111111111111111111111111111111111111111111111 ,
bx +
bx *
b11111111111111111111111111111111111111111111111111111111111111111111111111111111 )
b1111111111111111111111111111111111111111111111111111111111111111 (
1'
b11111111111111111111111111111111111111111111111111111111111111111111111111111111 &
0%
0$
x"
bx !
$end
#5000
b0 :
b1011101110110000 <
b10001000100000 @
b101110111011000000000000000000000010001000100000 .
b0 >
b0 9
b1011 ;
b10 ?
b0 =
b10 _
b1011 Q
b0 S
b101100000000000000000000000000000010 -
b101100000000000000000000000000000010 B
b1110 ^
b0 R
b0 E
b0 U
b0 W
b0 Y
b0 [
b0 ]
b0 a
b0 c
b0 G
b0 I
b0 K
b0 M
b101100000000000000000000000000000010000000000000000000000000 C
b0 O
b0 D
b0 T
b0 V
b0 X
b0 Z
b0 \
b0 `
b0 b
b0 F
b0 H
b0 J
b0 L
b0 N
b1000 P
b100000000000000000000000000000001110000000000000000000000000 +
b100000000000000000000000000000001110000000000000000000000000 A
b0 !
b0 *
b1 5
b1 8
b1111 7
b11110111111111111111111111111111111100011111111111111111111111111111111111111111 /
b11110111111111111111111111111111111100011111111111111111111111111111111111111111 6
b11111111111111111111111111111111111111111111111111111111111111111111111111111111 1
b11111111111111111111111111111111111111111111111111111111111111111111111111111111 4
b1111111111111111111111111111111111111111111111111111111111111111 2
b1 0
b1 3
0"
1$
#10000
0$
1%
#15000
b11011010101000 @
b1101110111010001 >
b100100011011000 <
b100011101110010010010001101100011011101110100010011011010101000 .
b100011101110010 :
b100000111011111 ?
b1000100011101 =
b1101000101000001 ;
b10000100010100 9
b10000100010100110100010100000100010001000111010100000111011111 -
b10000100010100110100010100000100010001000111010100000111011111 B
b1 E
b100 U
b100 W
b100 Y
b1 [
b1 ]
b1111 _
b1 a
b1 c
b1101 G
b1101 I
b1101 K
b1 M
b1 O
b1 Q
b10000100010001110111011101000100011111000100010100010001000001 C
b10 S
b1111 D
b1101 T
b1101 V
b1101 X
b1111 Z
b1111 \
b1 ^
b1111 `
b1111 b
b100 F
b100 H
b100 J
b1111 L
b1111 N
b1111 P
b1110 R
b1111011111111111010001000100111111110001111111111101110111011111 !
b1111011111111111010001000100111111110001111111111101110111011111 *
b1110111111111111010001000100111111110001111111111101110111011111 +
b1110111111111111010001000100111111110001111111111101110111011111 A
b11101111111111111111111111111111111100011111111111111111111111111000111110111111 /
b11101111111111111111111111111111111100011111111111111111111111111000111110111111 6
b11110111111111111111111111111111111100011111111111111111111111111111111111111111 1
b11110111111111111111111111111111111100011111111111111111111111111111111111111111 4
b101110111011000000000000000000000010001000100000 2
b10 0
b10 3
1$
#20000
0$
#25000
b1101000000 @
b1011000101100001 >
b1101110101001 <
b1011110111111000000110111010100110110001011000010000001101000000 .
b1011110111111000 :
b111010000110111 ?
b110110010111100 =
b1000001000110000 ;
b1010110011101001 9
b1010110011101001100000100011000001101100101111000111010000110111 -
b1010110011101001100000100011000001101100101111000111010000110111 B
b1100 E
b11 U
b1001 W
b111 Y
b10 [
b1110 ]
b111 _
b110 a
b1100 c
b11 G
b1100 I
b1000 K
b100 M
b1011 O
b0 Q
b1010000010110100100011000011110001100111111000100111100100111100 C
b1010 S
b111 D
b101 T
b1001 V
b1100 X
b1110 Z
b10 \
b1100 ^
b110 `
b111 b
b101 F
b111 H
b1011 J
b1101 L
b1000 N
b0 P
b1010 R
b1010100010001101101101110010011100101100001011101100100101010111 !
b1010100010001101101101110010011100101100001011101100100101010111 *
b1010000010001101101101110101011101101100001011101100100101010111 +
b1010000010001101101101110101011101101100001011101100100101010111 A
b11100111111111111111111110001111101100011111111111111111111111111000111101111111 /
b11100111111111111111111110001111101100011111111111111111111111111000111101111111 6
b11101111111111111111111111111111111100011111111111111111111111111000111110111111 1
b11101111111111111111111111111111111100011111111111111111111111111000111110111111 4
b100011101110010010010001101100011011101110100010011011010101000 2
b11 0
b11 3
1$
#30000
0$
#35000
b10111111010011 @
b1001101011100011 >
b1001100111100101 <
b1110111000011001100110011110010110011010111000110010111111010011 .
b1110111000011001 :
b1110011100000 ?
b111010000001101 =
b10001001011110 ;
b110011010010001 9
b110011010010001001000100101111001110100000011010001110011100000 -
b110011010010001001000100101111001110100000011010001110011100000 B
b100 E
b101 U
b1 W
b1 Y
b1001 ]
b0 _
b111 a
b110 c
b1110 G
b1101 I
b10 K
b1100 M
b0 O
b1110 Q
b110111000001100001011011110011001110000100100100001000101010100 C
b110 S
b1101 D
b11 T
b1111 V
b1111 X
b1001 \
b0 ^
b1100 `
b110 b
b10 F
b100 H
b1110 J
b111 L
b0 N
b10 P
b110 R
b101101000000111111001000010011000000000100111101111110010111111 !
b101101000000111111001000010011000000000100111101111110010111111 *
b110001000000111111001000010011011000000100111101111111100111101 +
b110001000000111111001000010011011000000100111101111111100111101 A
b11011111111111111111111110001111011100011111111111111100011111011000111100111111 /
b11011111111111111111111110001111011100011111111111111100011111011000111100111111 6
b11100111111111111111111110001111101100011111111111111111111111111000111101111111 1
b11100111111111111111111110001111101100011111111111111111111111111000111101111111 4
b1011110111111000000110111010100110110001011000010000001101000000 2
b100 0
b100 3
1$
#40000
0$
#45000
b1101101011110001 @
b100010111000011 >
b100000111001111 <
b111110100000010000011100111101000101110000111101101011110001 .
b111110100000 :
b100001101101000 ?
b1010101100101101 =
b10011110101001 ;
b101101011110101 9
b101101011110101001001111010100110101011001011010100001101101000 -
b101101011110101001001111010100110101011001011010100001101101000 B
b1011 E
b1010 U
b101 W
b100 Y
b111 [
b1111 ]
b1000 _
b1010 a
b1010 c
b110 G
b1101 I
b10 K
b11 M
b10 O
b1001 Q
b101100100100011001011010110101010101000111101110100010110101011 C
b101 S
b1000 D
b1010 T
b11 V
b1101 X
b1100 Z
b1 \
b1011 ^
b1010 `
b1010 b
b110 F
b100 H
b1110 J
b101 L
b1110 N
b1001 P
b11 R
b11000111100110011001100110101011101011000111001101001110101110 !
b11000111100110011001100110101011101011000111001101001110101110 *
b11100111100101111001000110101010101011000111001101001110101000 +
b11100111100101111001000110101010101011000111001101001110101000 A
b11010111111111000111110110001111001100011111111111111100011110111000111011111111 /
b11010111111111000111110110001111001100011111111111111100011110111000111011111111 6
b11011111111111111111111110001111011100011111111111111100011111011000111100111111 1
b11011111111111111111111110001111011100011111111111111100011111011000111100111111 4
b1110111000011001100110011110010110011010111000110010111111010011 2
b101 0
b101 3
1$
#50000
0$
#55000
b111010111111111 @
b10000110010000 >
b1011111001011110 <
b111111111100110101111100101111000100001100100000111010111111111 .
b111111111100110 :
b101011111011101 ?
b1000101100111010 =
b101000010110000 ;
b111111111100110 9
b0 [
b111111111100110010100001011000010001011001110100101011111011101 -
b111111111100110010100001011000010001011001110100101011111011101 B
b0 Z
b1011 E
b1011 U
b110 W
b101 Y
b1110 ]
b1101 _
b1000 a
b1111 c
b1101 G
b1010 I
b101 K
b111 M
b11 O
b0 Q
b111000000110111010110101101111110001101111000000101011010111011 C
b111 S
b1000 D
b1000 T
b110 V
b11 X
b10 \
b100 ^
b1011 `
b1 b
b100 F
b1010 H
b11 J
b1100 L
b101 N
b0 P
b1100 R
b1101100001011100001111000100000001110100001111000010011010001010 !
b1101100001011100001111000100000001110100001111000010011010001010 *
b1100000001011100001110100100000110110100001000000011011010001000 +
b1100000001011100001110100100000110110100001000000011011010001000 A
b11001111111111000111101110001110111100011110001111101100011110011000111010111111 /
b11001111111111000111101110001110111100011110001111101100011110011000111010111111 6
b11010111111111000111110110001111001100011111111111111100011110111000111011111111 1
b11010111111111000111110110001111001100011111111111111100011110111000111011111111 4
b111110100000010000011100111101000101110000111101101011110001 2
b110 0
b110 3
1$
#60000
0$
#65000
b11000111111001 <
b1110111000000100 @
b111010111100010 >
b101111100110110001100011111100101110101111000101110111000000100 .
b101111100110110 :
b111010110111101 ;
b1010101001000000 ?
b1001101100001100 =
b1010000011001001 9
b1101 Q
b1010000011001001011101011011110110011011000011001010101001000000 -
b1010000011001001011101011011110110011011000011001010101001000000 B
b100 P
b1011 E
b1001 W
b1010 Y
b101 [
b1100 ]
b0 _
b1001 a
b0 c
b100 G
b1100 I
b111 K
b1010 M
b0 O
b1010110100001010011111000100000010010000110001011010100110111011 C
b1010 S
b1000 D
b1001 V
b1010 X
b11 Z
b111 \
b0 ^
b1001 `
b0 b
b1101 F
b111 H
b1100 J
b1010 L
b0 N
b1010 R
b1011000000011010110001011101000011010000011100111001100110000110 !
b1011000000011010110001011101000011010000011100111001100110000110 *
b1010010000001010110001111101000010010000011100111010100110001000 +
b1010010000001010110001111101000010010000011100111010100110001000 A
b11011011111011000111100110001110101100011110001111011100011101111000111001111111 /
b11011011111011000111100110001110101100011110001111011100011101111000111001111111 6
b11001111111111000111101110001110111100011110001111101100011110011000111010111111 1
b11001111111111000111101110001110111100011110001111101100011110011000111010111111 4
b111111111100110101111100101111000100001100100000111010111111111 2
b111 0
b111 3
1$
#70000
0$
#75000
b1011111110011000 @
b100011001011110 <
b1011010010011101 >
b1001010000110110010001100101111010110100100111011011111110011000 .
b1001010000110110 :
b1110101011001101 ?
b1101111111000111 ;
b111100100110 =
b1110010111110 9
b111 Q
b1110010111110110111111100011100001111001001101110101011001101 -
b1110010111110110111111100011100001111001001101110101011001101 B
b1100 P
b1111 E
b1100 U
b1110 W
b1110 Y
b1111 [
b1011 ]
b1101 _
b0 a
b1100 c
b1100 G
b110 I
b1101 K
b10 O
b1011100101010110101101100110000001101101111111110111011001111 C
b1 S
b1 D
b111 T
b10 V
b10 X
b1 Z
b1000 \
b100 ^
b0 `
b111 b
b111 F
b110 H
b100 J
b1110 N
b1111 R
b1000010011011010010010000111011111000100000000010011001001110011 !
b1000010011011010010010000111011111000100000000010011001001110011 *
b1111110011101010010001100111011100000100100000010010001001110001 +
b1111110011101010010001100111011100000100100000010010001001110001 A
b10100011110111000111011110001110011100010110001111001100011101011000111011011111 /
b10100011110111000111011110001110011100010110001111001100011101011000111011011111 6
b11011011111011000111100110001110101100011110001111011100011101111000111001111111 1
b11011011111011000111100110001110101100011110001111011100011101111000111001111111 4
b101111100110110001100011111100101110101111000101110111000000100 2
b1000 0
b1000 3
1$
#80000
0$
#85000
b1101011110011110 @
b1100001010111111 >
b1011001100101 <
b1001000111010100000101100110010111000010101111111101011110011110 .
b1001000111010100 :
b101001000011 ?
b110100000010101 =
b101001000100001 ;
b1000000011000101 9
b1 O
b1000000011000101010100100010000101101000000101010000101001000011 -
b1000000011000101010100100010000101101000000101010000101001000011 B
b1111 N
b1000 E
b10 U
b101 W
b0 Y
b10 [
b1100 ]
b11 _
b110 a
b0 c
b100 G
b101 I
b101 K
b1 Q
b1000000100011010010101010100000001100011110000100000010100101000 C
b1000 S
b1011 D
b1110 T
b11 V
b0 X
b1110 Z
b111 \
b101 ^
b110 `
b0 b
b1101 F
b11 H
b11 J
b1111 P
b1011 R
b11011111101010001100011101000011000101111111100111001111101101 !
b11011111101010001100011101000011000101111111100111001111101101 *
b1011111111111010001100111101000001100101011111100000001111101011 +
b1011111111111010001100111101000001100101011111100000001111101011 A
b101011110011000111010110001110110100011110001110111100011100111000110100011110 /
b101011110011000111010110001110110100011110001110111100011100111000110100011110 6
b10100011110111000111011110001110011100010110001111001100011101011000111011011111 1
b10100011110111000111011110001110011100010110001111001100011101011000111011011111 4
b1001010000110110010001100101111010110100100111011011111110011000 2
b1001 0
b1001 3
1$
#90000
0$
#95000
b111001011010001 :
b1001111001110101 @
b1110000111001001 >
b111001011010001101110101111001111100001110010011001111001110101 .
b1011101011110011 <
b1110101101001000 9
b1100101100100000 ?
b100101101100011 =
b110011100101110 ;
b11 I
b1110 S
b1110101101001000011001110010111001001011011000111100101100100000 -
b1110101101001000011001110010111001001011011000111100101100100000 B
b101 H
b10 R
b1011 E
b1000 W
b1100 Y
b111 [
b100 ]
b0 _
b100 a
b1011 c
b10 G
b110 K
b1011 M
b110 O
b1110111001101011011000110010101101000000010001111100100000101011 C
b1110 Q
b10 5
b10 8
b1000 D
b1011 V
b111 X
b1100 Z
b1101 \
b0 ^
b1101 `
b1000 b
b1110 F
b110 J
b1000 L
b110 N
b10 P
b1110 7
b1011101000011000011000111110101100010011010111000110101111101101 !
b1011101000011000011000111110101100010011010111000110101111101101 *
b10001001101000011001011110100011010000110111000111101111101000 +
b10001001101000011001011110100011010000110111000111101111101000 A
b10110011101111000111001110001101000100100110001110101100011101101000100101011110 /
b10110011101111000111001110001101000100100110001110101100011101101000100101011110 6
b101011110011000111010110001110110100011110001110111100011100111000110100011110 1
b101011110011000111010110001110110100011110001110111100011100111000110100011110 4
b1001000111010100000101100110010111000010101111111101011110011110 2
b1010 0
b1010 3
1$
#100000
0$
#105000
b1111001110110000 >
b1101100100011000 @
b1100000101000010 <
b1010110110011001110000010100001011110011101100001101100100011000 .
b1010110110011001 :
b1000010011000111 =
b10011000101 ?
b111101011111001 ;
b1101101011101110 9
b1100 O
b1101101011101110011110101111100110000100110001110000010011000101 -
b1101101011101110011110101111100110000100110001110000010011000101 B
b111 N
b100 E
b1111 U
b1110 W
b0 Y
b1010 [
b1110 ]
b101 _
b1000 a
b1010 c
b1100 G
b111 I
b111 K
b100 M
b1001 Q
b1101100111000100011101111100101010000101111010100000111011110100 C
b1101 S
b1101 D
b1 T
b10 V
b0 X
b1010 Z
b10 \
b11 ^
b1011 `
b1010 b
b111 F
b1100 H
b1100 J
b1101 L
b1001 P
b100 R
b1100000101101101110010010111111011110011101010100011001000000011 !
b1100000101101101110010010111111011110011101010100011001000000011 *
b100100101111101110011000111101010110011001010100000001000011101 +
b100100101111101110011000111101010110011001010100000001000011101 A
b111011101011000111011010001001010100101110001110011100011010001001010110011101 /
b111011101011000111011010001001010100101110001110011100011010001001010110011101 6
b10110011101111000111001110001101000100100110001110101100011101101000100101011110 1
b10110011101111000111001110001101000100100110001110101100011101101000100101011110 4
b111001011010001101110101111001111100001110010011001111001110101 2
b1011 0
b1011 3
1$
#110000
0$
#115000
b1011111010010001 @
b111111100011000 >
b100101111011100 <
b1100111001100110010010111101110001111111000110001011111010010001 .
b1100111001100110 :
b110001101001100 ?
b110111000001001 =
b1010010100110010 ;
b1110110001000100 9
b1110110001000100101001010011001001101110000010010110001101001100 -
b1110110001000100101001010011001001101110000010010110001101001100 B
b1110 E
b11 U
b100 W
b110 Y
b101 [
b100 ]
b1100 _
b110 a
b1100 c
b100 G
b1001 I
b1010 K
b11 M
b0 O
b10 Q
b1110001000000011101010010100110001101100010001010110010000111110 C
b1110 S
b100 5
b100 8
b10 D
b101 T
b1101 V
b110 X
b11 Z
b1101 \
b111 ^
b110 `
b111 b
b1101 F
b1001 H
b1010 J
b101 L
b0 N
b1110 P
b10 R
b1101 7
b1001011000110101101101111100101110100001010100110100010101110000 !
b1001011000110101101101111100101110100001010100110100010101110000 *
b10111000000101101010011101011101100111110100110110110101010010 +
b10111000000101101010011101011101100111110100110110110101010010 A
b10000011100111000110100010010101100101000110001110110100010010101001000111011101 /
b10000011100111000110100010010101100101000110001110110100010010101001000111011101 6
b111011101011000111011010001001010100101110001110011100011010001001010110011101 1
b111011101011000111011010001001010100101110001110011100011010001001010110011101 4
b1010110110011001110000010100001011110011101100001101100100011000 2
b1100 0
b1100 3
1$
#120000
0$
#125000
b1011010001110010 @
b1111000100011010 >
b1110011010111101 <
b1111110010010010111001101011110111110001000110101011010001110010 .
b1111110010010010 :
b1111011011000 ?
b1010010001001111 =
b100001010011 ;
b111010000011010 9
b111010000011010000010000101001110100100010011110001111011011000 -
b111010000011010000010000101001110100100010011110001111011011000 B
b100 E
b101 U
b1010 W
b1 Y
b1000 [
b1 ]
b1000 _
b1010 a
b100 c
b1101 G
b1111 I
b0 K
b1110 M
b100 O
b11 Q
b111001101001110000011111101010010101000000110000001101001010100 C
b111 S
b1101 D
b11 T
b1010 V
b1111 X
b1011 Z
b1111 \
b1011 ^
b1010 `
b1101 b
b100 F
b1 H
b0 J
b10 L
b1101 N
b101 P
b1100 R
b100110111111010001000110100100111101011011110110000101011011011 !
b100110111111010001000110100100111101011011110110000101011011011 *
b1100010111010010000000010100110110101011111110111111101000111101 +
b1100010111010010000000010100110110101011111110111111101000111101 A
b1011101101000100101010010001110101001110001101000100101011001010010000011100 /
b1011101101000100101010010001110101001110001101000100101011001010010000011100 6
b10000011100111000110100010010101100101000110001110110100010010101001000111011101 1
b10000011100111000110100010010101100101000110001110110100010010101001000111011101 4
b1100111001100110010010111101110001111111000110001011111010010001 2
b1101 0
b1101 3
1$
#130000
0$
#135000
b1111101100101011 @
b1001110011110001 >
b1011110101110111 <
b1111011110111101111010111011110011100111100011111101100101011 .
b1111011110111 :
b10011011110110 ?
b10011101001010 =
b1101101100010001 ;
b110100110000000 9
b10 Y
b1000 ]
b110100110000000110110110001000100100111010010100010011011110110 -
b110100110000000110110110001000100100111010010100010011011110110 B
b1110 X
b1011 \
b111 E
b1 U
b0 W
b1011 [
b110 _
b10 a
b1001 c
b1111 G
b1010 I
b1101 K
b110 M
b100 O
b1 Q
b110000101000110110110101111100100100110100010110010000000010111 C
b110 S
b111 5
b111 8
b1100 D
b1111 T
b0 V
b1000 Z
b110 ^
b1110 `
b1001 b
b1 F
b1010 H
b100 J
b110 L
b1101 N
b1111 P
b110 R
b1100 7
b1111011100100110101011000010110000100101111110011111000011011110 !
b1111011100100110101011000010110000100101111110011111000011011110 *
b110111111010110010010100001100111100110101110001110000011111100 +
b110111111010110010010100001100111100110101110001110000011111100 A
b10010011010001001010110010100100000101111010001001010100100011101010000001011101 /
b10010011010001001010110010100100000101111010001001010100100011101010000001011101 6
b1011101101000100101010010001110101001110001101000100101011001010010000011100 1
b1011101101000100101010010001110101001110001101000100101011001010010000011100 4
b1111110010010010111001101011110111110001000110101011010001110010 2
b1110 0
b1110 3
1$
#140000
0$
#145000
b1010011001111000 @
b111100010100101 >
b100001011000 <
b1010000110011111000010000101100001111000101001011010011001111000 .
b1010000110011111 :
b1001010101001011 ?
b111100010100101 =
b101110100001101 ;
b111110001000010 9
b111110001000010010111010000110101111000101001011001010101001011 -
b111110001000010010111010000110101111000101001011001010101001011 B
b1000 E
b0 U
b10 W
b1001 Y
b1101 [
b100 ]
b1011 _
b111 a
b1100 c
b100 G
b101 I
b101 K
b101 M
b1010 O
b1101 Q
b111110110100101010101010100110001111011010011011001001000001000 C
b111 S
b100 5
b100 8
b1011 D
b0 T
b1110 V
b1001 X
b100 Z
b1101 \
b1000 ^
b1100 `
b111 b
b1101 F
b11 H
b11 J
b11 L
b1010 N
b100 P
b1100 R
b1101 7
b1000110110110011000100011101001110001011010100111010111110100101 !
b1000110110110011000100011101001110001011010100111010111110100101 *
b1100010010100011001100111101011111001000110101001001111000001011 +
b1100010010100011001100111101011111001000110101001001111000001011 A
b11011010010101001000111010100000010101000010010101100101001000001011110010011010 /
b11011010010101001000111010100000010101000010010101100101001000001011110010011010 6
b10010011010001001010110010100100000101111010001001010100100011101010000001011101 1
b10010011010001001010110010100100000101111010001001010100100011101010000001011101 4
b1111011110111101111010111011110011100111100011111101100101011 2
b1111 0
b1111 3
1$
#150000
0$
#155000
b110100000001100 @
b100000111001 >
b1110111111001101 <
b1000010110001101111011111100110100001000001110010110100000001100 .
b1000010110001101 :
b100101000101110 ?
b10101000011011 =
b1110111111001101 ;
b110100000101 9
b110100000101111011111100110100101010000110110100101000101110 -
b110100000101111011111100110100101010000110110100101000101110 B
b1010 E
b1100 U
b101 W
b100 Y
b1111 [
b0 ]
b1110 _
b10 a
b1101 c
b10 G
b1011 I
b1110 K
b1010 M
b1 O
b1101 Q
b110100011010111010110010110100101110000011110100010111001010 C
b0 S
b1010 5
b1010 8
b1010 D
b111 T
b11 V
b1101 X
b1 Z
b0 \
b10 ^
b1110 `
b100 b
b1110 F
b1000 H
b10 J
b1010 L
b1111 N
b100 P
b0 R
b1010 7
b111101111001011100001101111100000101100100000001100001101011000 !
b111101111001011100001101111100000101100100000001100001101011000 *
b10011111010001010001110010011100010000000011101001101111010 +
b10011111010001010001110010011100010000000011101001101111010 A
b10100101011001010010000010111100100110101010010001110101000000101010011011010010 /
b10100101011001010010000010111100100110101010010001110101000000101010011011010010 6
b11011010010101001000111010100000010101000010010101100101001000001011110010011010 1
b11011010010101001000111010100000010101000010010101100101001000001011110010011010 4
b1010000110011111000010000101100001111000101001011010011001111000 2
b10000 0
b10000 3
1$
#160000
0$
