rtl/F2.v
//////////////////////////////////////////////////////////////////////////////////
// Company: 
// Engineer: 
// 
// Create Date:    17:35:22 05/30/2021 
// Design Name: 
// Module Name:    F2 
// Project Name: 
// Target Devices: 
// Tool versions: 
// Description: 
//
// Dependencies: 
//
// Revision: 
// Revision 0.01 - File Created
// Additional Comments: 
//
//////////////////////////////////////////////////////////////////////////////////
module F2(w,rkey,W1);
  input[0:31] w;
  input[0:31] rkey;
  output[0:31] W1;
  wire[0:7] Row[0:3];
  wire[0:31] T;
  assign T=w^rkey;
  assign Row[0]=T[24:31];
  assign Row[1]={T[18:23],T[16:17]};
  assign Row[2]={T[11:15],T[8:10]};
  assign Row[3]={T[6:7],T[0:5]};
  assign W1={Row[3],Row[2],Row[1],Row[0]};

endmodule

rtl/F1.v
//////////////////////////////////////////////////////////////////////////////////
// Company: 
// Engineer: 
// 
// Create Date:    17:34:49 05/30/2021 
// Design Name: 
// Module Name:    F1 
// Project Name: 
// Target Devices: 
// Tool versions: 
// Description: 
//
// Dependencies: 
//
// Revision: 
// Revision 0.01 - File Created
// Additional Comments: 
//
//////////////////////////////////////////////////////////////////////////////////
module F1(w,rkey,W1);
  input[0:31] w;
  input[0:31] rkey;
  output[0:31] W1;
  wire[0:7] Row[0:3];
  wire[0:31] T;
  assign T=w^rkey;
  assign Row[0]=T[24:31];
  assign Row[1]={T[17:23],T[16]};
  assign Row[2]={T[12:15],T[8:11]};
  assign Row[3]={T[5:7],T[0:4]};
  assign W1={Row[3],Row[2],Row[1],Row[0]};

endmodule

rtl/fS.v
//////////////////////////////////////////////////////////////////////////////////
// Company: 
// Engineer: 
// 
// Create Date:    17:34:21 05/30/2021 
// Design Name: 
// Module Name:    fS 
// Project Name: 
// Target Devices: 
// Tool versions: 
// Description: 
//
// Dependencies: 
//
// Revision: 
// Revision 0.01 - File Created
// Additional Comments: 
//
//////////////////////////////////////////////////////////////////////////////////
module fS(W,rkey,w1);
  input[0:31] W;
  input[0:31] rkey;
  output[0:31] w1;
  wire[0:7] s[1:7];
 
 
  assign s[1]=~(W[16:23]);
  assign s[2]=(W[24:31]&s[1]);
  assign s[3]=(W[8:15]^W[0:7]);

  assign w1[16:23]=s[3]^s[2];
  assign s[4]=(W[0:7]|s[1]);
  assign s[5]=((W[24:31]^s[4]));

  assign w1[24:31]=W[8:15]^s[5];
  assign s[6]=(W[16:23]^W[8:15]);
  assign s[7]=(s[3]&s[6]);

  assign w1[8:15]=s[6]^s[7];
  assign w1[0:7]=((rkey[24:31]&rkey[16:23])&((~W[8:15]&~W[16:23])|(W[0:7]&~W[16:23]&~W[24:31])|(~W[0:7]&~W[16:23]&W[24:31])|(~W[0:7]&W[8:15]&W[16:23])))|
		 (((rkey[0:7]^rkey[8:15])&~rkey[24:31])&((~W[0:7]&~W[16:23]&W[24:31])|(~W[8:15]&W[16:23]&~W[24:31])|(W[0:7]&W[16:23]&W[24:31])|(W[0:7]&~W[8:15])))|
		 
		 ((~(rkey[0:7]^rkey[8:15])&~rkey[24:31])&((~W[8:15]&~W[24:31])|(~W[0:7]&~W[16:23]&~W[24:31])|(W[0:7]&~W[8:15]&~W[16:23])|(~W[0:7]&W[16:23]&W[24:31])))|
		
		 ((~rkey[16:23]&rkey[24:31])&((~W[0:7]&~W[16:23]&W[24:31])|(W[0:7]&W[16:23]&W[24:31])|(W[8:15]&W[16:23]&~W[24:31])|(W[0:7]&W[8:15])));
		 

 

endmodule

rtl/fesitel.v
//////////////////////////////////////////////////////////////////////////////////
// Company: 
// Engineer: 
// 
// Create Date:    17:29:37 05/30/2021 
// Design Name: 
// Module Name:    fesitel 
// Project Name: 
// Target Devices: 
// Tool versions: 
// Description: 
//
// Dependencies: 
//
// Revision: 
// Revision 0.01 - File Created
// Additional Comments: 
//
//////////////////////////////////////////////////////////////////////////////////
module fesitel(plain,rkey,cipher);
  input[0:127] plain;
  input[0:31] rkey;
  output[0:127] cipher;
  wire[0:31] c0,c1,c2,c3,W,w1,f1,f2,f11,f21;
  assign c0=plain[0:31];
  assign c1=plain[32:63];
  assign c2=plain[64:95];
  assign c3=plain[96:127];
  assign W=c1^c2;
  fS t(W,rkey,w1);
  F1 a(w1,rkey,f1);
  F2 b(w1,rkey,f2);
  assign f11=f1^c0;
  assign f21=f2^c3;
  assign cipher={c2,f21,f11,c1};
  
endmodule

rtl/one_fesitel.v
//////////////////////////////////////////////////////////////////////////////////
// Company: 
// Engineer: 
// 
// Create Date:    17:30:59 05/30/2021 
// Design Name: 
// Module Name:    one_fesitel 
// Project Name: 
// Target Devices: 
// Tool versions: 
// Description: 
//
// Dependencies: 
//
// Revision: 
// Revision 0.01 - File Created
// Additional Comments: 
//
//////////////////////////////////////////////////////////////////////////////////
module one_fesitel(row00,row11,row22,row33,tt,w00,w11,w22,w33);
  input[0:15] row00;
  input[0:15] row11;
  input[0:15] row22;
  input[0:15] row33;
  input[0:31] tt;
  output[0:15] w00;
  output[0:15] w11;
  output[0:15] w22;
  output[0:15] w33;
  wire[0:15] Row[0:1];
 
  
  
  assign Row[0]=row00;
  
  assign Row[1]=row22;
  
  assign w00=Row[0]^row11;
  assign w11=row22;
  assign w22=Row[1]^row33;
  assign w33=row00;

endmodule

rtl/eS.v
//////////////////////////////////////////////////////////////////////////////////
// Company: 
// Engineer: 
// 
// Create Date:    17:30:20 05/30/2021 
// Design Name: 
// Module Name:    eS 
// Project Name: 
// Target Devices: 
// Tool versions: 
// Description: 
//
// Dependencies: 
//
// Revision: 
// Revision 0.01 - File Created
// Additional Comments: 
//
//////////////////////////////////////////////////////////////////////////////////
module eS(Row0,Row1,Row2,Row3,rkey,row00,row11,row22,row33);
  input[0:15] Row0;
  input[0:15] Row1;
  input[0:15] Row2;
  input[0:15] Row3;
  input[0:31] rkey;
  output[0:15] row00;
  output[0:15] row11;
  output[0:15] row22;
  output[0:15] row33;
  wire[0:7] s0,s1,s2,s3,s[1:7];
  
 
  assign s[1]=~(Row1[8:15]);
  assign s[2]=(Row0[8:15]&s[1]);
  assign s[3]=(Row2[8:15]^Row3[8:15]);

  assign s1=s[3]^s[2];
  assign s[4]=(Row3[8:15]|s[1]);
  assign s[5]=((Row0[8:15]^s[4]));

  assign s0=Row2[8:15]^s[5];
  assign s[6]=(Row1[8:15]^Row2[8:15]);
  assign s[7]=(s[3]&s[5]);

  assign s2=s[6]^s[7];
  assign s3=((rkey[24:31]&rkey[16:23])&((~Row2[8:15]&~Row1[8:15])|(Row3[8:15]&~Row1[8:15]&~Row0[8:15])|(~Row3[8:15]&~Row1[8:15]&Row0[8:15])|(~Row3[8:15]&Row2[8:15]&Row1[8:15])))|
		 (((rkey[0:7]^rkey[8:15])&~rkey[24:31])&((~Row3[8:15]&~Row1[8:15]&Row0[8:15])|(~Row2[8:15]&Row1[8:15]&~Row0[8:15])|(Row3[8:15]&Row1[8:15]&Row0[8:15])|(Row3[8:15]&~Row2[8:15])))|
		 
		 ((~(rkey[0:7]^rkey[8:15])&~rkey[24:31])&((~Row2[8:15]&~Row0[8:15])|(~Row3[8:15]&~Row1[8:15]&~Row0[8:15])|(Row3[8:15]&~Row2[8:15]&~Row1[8:15])|(~Row3[8:15]&Row1[8:15]&Row0[8:15])))|
		
		 ((~rkey[16:23]&rkey[24:31])&((~Row3[8:15]&~Row1[8:15]&Row0[8:15])|(Row3[8:15]&Row1[8:15]&Row0[8:15])|(Row2[8:15]&Row1[8:15]&~Row0[8:15])|(Row3[8:15]&Row2[8:15])));
		 

  
  assign row00={Row0[0:7],s0};
  assign row11={Row1[0:7],s1};
  assign row22={Row2[0:7],s2};
  assign row33={Row3[0:7],s3};

endmodule

rtl/expandrey.v
//////////////////////////////////////////////////////////////////////////////////
// Company: 
// Engineer: 
// 
// Create Date:    17:29:02 05/30/2021 
// Design Name: 
// Module Name:    expandrey 
// Project Name: 
// Target Devices: 
// Tool versions: 
// Description: 
//
// Dependencies: 
//
// Revision: 
// Revision 0.01 - File Created
// Additional Comments: 
//
//////////////////////////////////////////////////////////////////////////////////
module expandrey(Key,i,tt,rkey,key11);
  input[0:63] Key;
  input[0:5] i;
  input[0:31] tt;
  input[0:31] rkey;
  output[0:63] key11;
  wire[0:4] b,d,x1[0:3],x2[0:3];
  wire[0:15] Row[0:3],row1[0:3],w[0:3],z;
  assign Row[0]=Key[48:63];
  assign Row[1]=Key[32:47];
  assign Row[2]=Key[16:31];
  assign Row[3]=Key[0:15];
 
  
  eS s(Row[0],Row[1],Row[2],Row[3],rkey,row1[0],row1[1],row1[2],row1[3]);
  one_fesitel one(row1[0],row1[1],row1[2],row1[3],tt,w[0],w[1],w[2],w[3]);

  
  assign b=w[3][0:4];
  assign d=b^i;
  assign z={d[0:4],w[3][5:15]};

  assign key11={z,w[2],w[1],w[0]};

endmodule

rtl/encrytion.v
//////////////////////////////////////////////////////////////////////////////////
// Company:
// Engineer:
//
// Create Date:    17:28:13 05/30/2021
// Design Name:
// Module Name:    encrytion
// Project Name:
// Target Devices:
// Tool versions:
// Description:
//
// Dependencies:
//
// Revision:
// Revision 0.01 - File Created
// Additional Comments:
//
//////////////////////////////////////////////////////////////////////////////////
module encrytion(Plain,
                 Key,
                 clock,
                 encrypt_start, // start encrypt
                 encrypt_end,   // encrypt finish
                 Cipher);
    input [0:127] Plain;
    input [0:63] Key;
    input encrypt_start;
    input clock;
    output reg encrypt_end;
    output [0:127] Cipher;
    reg[0:5] r;
    reg[0:31] rkey1;
    reg[0:127] cipher2;
    reg [0:63] Key1;
    reg[0:31] t1;
    wire[0:63] key11;
    wire[0:127] cipher3;
    wire[0:31] rt;
    
    
    always @(posedge clock)
    begin
        r <= (encrypt_start)?r+1:1;
        rkey1 = (encrypt_start)?key11[0:31]:Key[0:31];
        Key1  = (encrypt_start)?key11:Key;
        cipher2 <= (encrypt_start)?cipher3:Plain;
    end
    
    // end encrypt if encrypt finish by r
    always @(posedge  clock) begin
        if (r > 31 && encrypt_start) begin
            encrypt_end = 1;
        end
        else begin
            encrypt_end = 0;
        end
    end
    
    expandrey c(Key1,r,t1,rkey1,key11);
    fesitel d(cipher2,rkey1,cipher3);
    assign Cipher = {cipher2[64:95],cipher2[96:127],cipher2[0:31],cipher2[32:63]};
endmodule

rtl/tb_i.v
`timescale  1ns / 1ps

module tb_i();
    parameter PERIOD = 10;
    reg clk;
    reg rst_n;
    reg encrypt_start;
    reg [0:127] state;
    reg [0:63] keys;
    reg [23:0] counter;
    wire  encrypt_end;
    wire [0:127] result;
    // generate colck
    initial begin
        rst_n         = 1'b1;
        clk           = 1'b0;
        encrypt_start = 1'b0;
        forever #(PERIOD/2)
            clk = ~clk;
        
    end
    
    initial begin
        state = 128'hffff_ffff_ffff_ffff_ffff_ffff_ffff_ffff;
        keys  = 64'h0000_0000_0000_0000;
        #(PERIOD)
        encrypt_start = 1'b1;
    end
    
    
    always @(posedge clk) begin
        if (encrypt_end) begin
            encrypt_start <= 0;
        end
    end
    
    encrytion u_d(
    .Plain(state),
    .Key(keys),
    .clock(clk),
    .encrypt_start(encrypt_start),
    .encrypt_end(encrypt_end),
    .Cipher(result)
    );
    
    
    initial begin
        $dumpfile("./wave.vcd");
        $dumpvars(0, tb_i);
        #(PERIOD*40) $finish;
    end
    
endmodule

rtl/wave.vcd
$date
	Thu Mar 30 08:58:48 2023
$end
$version
	Icarus Verilog
$end
$timescale
	1ps
$end
$scope module tb_i $end
$var wire 128 ! result [0:127] $end
$var wire 1 " encrypt_end $end
$var parameter 32 # PERIOD $end
$var reg 1 $ clk $end
$var reg 1 % encrypt_start $end
$var reg 64 & keys [0:63] $end
$var reg 1 ' rst_n $end
$var reg 128 ( state [0:127] $end
$scope module u_d $end
$var wire 64 ) Key [0:63] $end
$var wire 128 * Plain [0:127] $end
$var wire 1 $ clock $end
$var wire 1 % encrypt_start $end
$var wire 64 + key11 [0:63] $end
$var wire 128 , cipher3 [0:127] $end
$var wire 128 - Cipher [0:127] $end
$var reg 64 . Key1 [0:63] $end
$var reg 128 / cipher2 [0:127] $end
$var reg 1 " encrypt_end $end
$var reg 6 0 r [0:5] $end
$var reg 32 1 rkey1 [0:31] $end
$var reg 32 2 t1 [0:31] $end
$scope module c $end
$var wire 64 3 Key [0:63] $end
$var wire 6 4 i [0:5] $end
$var wire 32 5 rkey [0:31] $end
$var wire 32 6 tt [0:31] $end
$var wire 16 7 z [0:15] $end
$var wire 64 8 key11 [0:63] $end
$var wire 5 9 d [0:4] $end
$var wire 5 : b [0:4] $end
$scope module one $end
$var wire 32 ; tt [0:31] $end
$var wire 16 < w00 [0:15] $end
$var wire 16 = w11 [0:15] $end
$var wire 16 > w22 [0:15] $end
$var wire 16 ? w33 [0:15] $end
$var wire 16 @ row33 [0:15] $end
$var wire 16 A row22 [0:15] $end
$var wire 16 B row11 [0:15] $end
$var wire 16 C row00 [0:15] $end
$upscope $end
$scope module s $end
$var wire 16 D Row0 [0:15] $end
$var wire 16 E Row1 [0:15] $end
$var wire 16 F Row2 [0:15] $end
$var wire 16 G Row3 [0:15] $end
$var wire 32 H rkey [0:31] $end
$var wire 8 I s0 [0:7] $end
$var wire 8 J s1 [0:7] $end
$var wire 8 K s2 [0:7] $end
$var wire 8 L s3 [0:7] $end
$var wire 16 M row33 [0:15] $end
$var wire 16 N row22 [0:15] $end
$var wire 16 O row11 [0:15] $end
$var wire 16 P row00 [0:15] $end
$upscope $end
$upscope $end
$scope module d $end
$var wire 32 Q W [0:31] $end
$var wire 32 R f11 [0:31] $end
$var wire 32 S f21 [0:31] $end
$var wire 128 T plain [0:127] $end
$var wire 32 U rkey [0:31] $end
$var wire 32 V w1 [0:31] $end
$var wire 32 W f2 [0:31] $end
$var wire 32 X f1 [0:31] $end
$var wire 128 Y cipher [0:127] $end
$var wire 32 Z c3 [0:31] $end
$var wire 32 [ c2 [0:31] $end
$var wire 32 \ c1 [0:31] $end
$var wire 32 ] c0 [0:31] $end
$scope module a $end
$var wire 32 ^ T [0:31] $end
$var wire 32 _ rkey [0:31] $end
$var wire 32 ` w [0:31] $end
$var wire 32 a W1 [0:31] $end
$upscope $end
$scope module b $end
$var wire 32 b T [0:31] $end
$var wire 32 c rkey [0:31] $end
$var wire 32 d w [0:31] $end
$var wire 32 e W1 [0:31] $end
$upscope $end
$scope module t $end
$var wire 32 f W [0:31] $end
$var wire 32 g rkey [0:31] $end
$var wire 32 h w1 [0:31] $end
$upscope $end
$upscope $end
$upscope $end
$upscope $end
$enddefinitions $end
$comment Show the parameter values. $end
$dumpall
b1010 #
$end
#0
$dumpvars
bx h
bx g
bx f
bx e
bx d
bx c
bx b
bx a
bx `
bx _
bx ^
bx ]
bx \
bx [
bx Z
bx Y
bx X
bx W
bx V
bx U
bx T
bx S
bx R
bx Q
bx P
bx O
bx N
bx M
bx L
bx K
bx J
bx I
bx H
bx G
bx F
bx E
bx D
bx C
bx B
bx A
bx @
bx ?
bx >
bx =
bx <
bx ;
bx :
bx 9
bx 8
bx 7
bx 6
bx 5
bx 4
bx 3
bx 2
bx 1
bx 0
bx /
bx .
bx -
bx ,
bx +
b11111111111111111111111111111111111111111111111111111111111111111111111111111111111111111111111111111111111111111111111111111111 *
b0 )
b11111111111111111111111111111111111111111111111111111111111111111111111111111111111111111111111111111111111111111111111111111111 (
1'
b0 &
0%
0$
x"
bx !
$end
#5000
b111111111111111100000000 S
b111111111111111100000000 R
b11111111000000000000000011111111 W
b11111111000000000000000011111111 e
b11111111000000000000000011111111 X
b11111111000000000000000011111111 a
b11111111000000000000000011111111 b
b11111111000000000000000011111111 ^
b11111111000000000000000011111111 V
b11111111000000000000000011111111 `
b11111111000000000000000011111111 d
b11111111000000000000000011111111 h
b0 Q
b0 f
b1 9
b11111111111111111111111111111111111111111111111111111111111111111111111111111111111111111111111111111111111111111111111111111111 !
b11111111111111111111111111111111111111111111111111111111111111111111111111111111111111111111111111111111111111111111111111111111 -
b11111111111111111111111111111111 ]
b11111111111111111111111111111111 \
b11111111111111111111111111111111000000001111111111111111000000000000000011111111111111110000000011111111111111111111111111111111 ,
b11111111111111111111111111111111000000001111111111111111000000000000000011111111111111110000000011111111111111111111111111111111 Y
b11111111111111111111111111111111 [
b11111111111111111111111111111111 Z
b11111111111111111111111111111111111111111111111111111111111111111111111111111111111111111111111111111111111111111111111111111111 /
b11111111111111111111111111111111111111111111111111111111111111111111111111111111111111111111111111111111111111111111111111111111 T
b1 0
b1 4
b11111111 L
b11111111 I
b0 K
b0 J
b100011111111 7
b0 :
b11111111 <
b11111111 >
b11111111 ?
b11111111 C
b11111111 P
b0 B
b0 O
b100011111111000000001111111100000000000000000000000011111111 +
b100011111111000000001111111100000000000000000000000011111111 8
b0 =
b0 A
b0 N
b11111111 @
b11111111 M
b0 D
b0 E
b0 F
b0 G
b0 .
b0 3
b0 1
b0 5
b0 H
b0 U
b0 _
b0 c
b0 g
0"
1$
#10000
0$
1%
#15000
b10 9
b111111111111111100000000111111111111111111111111111111111111111111111111111111111111111100000000111111111111111100000000 !
b111111111111111100000000111111111111111111111111111111111111111111111111111111111111111100000000111111111111111100000000 -
b111111111111111100000000 \
b111111111111111100000000 [
b11111111111111111111111111111111000000001111111111111111000000000000000011111111111111110000000011111111111111111111111111111111 /
b11111111111111111111111111111111000000001111111111111111000000000000000011111111111111110000000011111111111111111111111111111111 T
b10 0
b10 4
b11111111 V
b11111111 `
b11111111 d
b11111111 h
b11111111 B
b11111111 O
b11111111 J
b1000011111111 7
b0 <
b11111111 =
b11111111 A
b11111111 N
b11111111 K
b11111111 ?
b11111111 C
b11111111 P
b11111111 I
b1000011111111000010000000000000000000111111110000000000000000 +
b1000011111111000010000000000000000000111111110000000000000000 8
b100000000000 >
b11111110000000001111111111111111 R
b111111111111111100000000111111010000000011111111111111111111111000000000111111111111111100000000111111111111111100000000 ,
b111111111111111100000000111111010000000011111111111111111111111000000000111111111111111100000000111111111111111100000000 Y
b11111101000000001111111111111111 S
b100011111111 @
b100011111111 M
b1111111110000000000000000 X
b1111111110000000000000000 a
b10111111110000000000000000 W
b10111111110000000000000000 e
b11111111 D
b11111111 F
b100011111111 G
b1000111111110000000000000000 ^
b1000111111110000000000000000 b
b100011111111000000001111111100000000000000000000000011111111 .
b100011111111000000001111111100000000000000000000000011111111 3
b1000111111110000000011111111 1
b1000111111110000000011111111 5
b1000111111110000000011111111 H
b1000111111110000000011111111 U
b1000111111110000000011111111 _
b1000111111110000000011111111 c
b1000111111110000000011111111 g
1$
#20000
0$
#25000
b11000000000000000000000000 Q
b11000000000000000000000000 f
b11 9
b11111110000000001111111111111111000000001111111111111111000000000000000011111111111111110000000011111101000000001111111111111111 !
b11111110000000001111111111111111000000001111111111111111000000000000000011111111111111110000000011111101000000001111111111111111 -
b111111111111111100000000 ]
b11111101000000001111111111111111 \
b11111110000000001111111111111111 [
b111111111111111100000000 Z
b111111111111111100000000111111010000000011111111111111111111111000000000111111111111111100000000111111111111111100000000 /
b111111111111111100000000111111010000000011111111111111111111111000000000111111111111111100000000111111111111111100000000 T
b11 0
b11 4
b10011000000000000001111111111 V
b10011000000000000001111111111 `
b10011000000000000001111111111 d
b10011000000000000001111111111 h
b0 K
b1100011111111 7
b0 <
b11111111 L
b11111111 ?
b11111111 C
b11111111 P
b11111111 I
b1100011111111 >
b1100000000000001110100111111111 R
b11111110000000001111111111111111110000000000000011010011111111110110000000000000111010011111111111111101000000001111111111111111 ,
b11111110000000001111111111111111110000000000000011010011111111110110000000000000111010011111111111111101000000001111111111111111 Y
b11000000000000001101001111111111 S
b1100011111111000110001111111100001000000000000000000000000000 +
b1100011111111000110001111111100001000000000000000000000000000 8
b100000000000 =
b100000000000 A
b100000000000 N
b1000011111111 @
b1000011111111 M
b1100000111111110001011011111111 X
b1100000111111110001011011111111 a
b11000000111111110010110011111111 W
b11000000111111110010110011111111 e
b0 D
b11111111 E
b100000000000 F
b1000011111111 G
b11111111110000101111111111 ^
b11111111110000101111111111 b
b1000011111111000010000000000000000000111111110000000000000000 .
b1000011111111000010000000000000000000111111110000000000000000 3
b10000111111110000100000000000 1
b10000111111110000100000000000 5
b10000111111110000100000000000 H
b10000111111110000100000000000 U
b10000111111110000100000000000 _
b10000111111110000100000000000 c
b10000111111110000100000000000 g
1$
#30000
0$
#35000
b10100000000000000011101000000000 Q
b10100000000000000011101000000000 f
b100 9
b1100000000000001110100111111111111111010000000011111111111111111111111000000000111111111111111111000000000000001101001111111111 !
b1100000000000001110100111111111111111010000000011111111111111111111111000000000111111111111111111000000000000001101001111111111 -
b11111110000000001111111111111111 ]
b11000000000000001101001111111111 \
b1100000000000001110100111111111 [
b11111101000000001111111111111111 Z
b11111110000000001111111111111111110000000000000011010011111111110110000000000000111010011111111111111101000000001111111111111111 /
b11111110000000001111111111111111110000000000000011010011111111110110000000000000111010011111111111111101000000001111111111111111 T
b100 0
b100 4
b11111111 L
b110101010000011100101 V
b110101010000011100101 `
b110101010000011100101 d
b110101010000011100101 h
b11111111 K
b0 J
b10000000000000 7
b100000000000 <
b0 ?
b0 C
b0 P
b0 I
b0 >
b11111101010111101000111011100101 R
b1100000000000001110100111111111111110110010111100011101111001011111110101011110100011101110010111000000000000001101001111111111 ,
b1100000000000001110100111111111111110110010111100011101111001011111110101011110100011101110010111000000000000001101001111111111 Y
b11111011001011110001110111100101 S
b100000000000 B
b100000000000 O
b10000000000000000000000000000000011000111111110000100000000000 +
b10000000000000000000000000000000011000111111110000100000000000 8
b1100011111111 =
b1100011111111 A
b1100011111111 N
b1100011111111 @
b1100011111111 M
b11010111100111000100011010 X
b11010111100111000100011010 a
b110001011111110001000011010 W
b110001011111110001000011010 e
b100000000000 E
b1100011111111 F
b1100011111111 G
b11000111001011011100000011010 ^
b11000111001011011100000011010 b
b1100011111111000110001111111100001000000000000000000000000000 .
b1100011111111000110001111111100001000000000000000000000000000 3
b11000111111110001100011111111 1
b11000111111110001100011111111 5
b11000111111110001100011111111 H
b11000111111110001100011111111 U
b11000111111110001100011111111 _
b11000111111110001100011111111 c
b11000111111110001100011111111 g
1$
#40000
0$
#45000
b110011100011001001100000000 Q
b110011100011001001100000000 f
b11111101010111101000111011100101110000000000000011010011111111110110000000000000111010011111111111111011001011110001110111100101 !
b11111101010111101000111011100101110000000000000011010011111111110110000000000000111010011111111111111011001011110001110111100101 -
b1100000000000001110100111111111 ]
b11111011001011110001110111100101 \
b11111101010111101000111011100101 [
b11000000000000001101001111111111 Z
b1100000000000001110100111111111111110110010111100011101111001011111110101011110100011101110010111000000000000001101001111111111 /
b1100000000000001110100111111111111110110010111100011101111001011111110101011110100011101110010111000000000000001101001111111111 T
b101 0
b101 4
b11001110100000000111011100011111 V
b11001110100000000111011100011111 `
b11001110100000000111011100011111 d
b11001110100000000111011100011111 h
b100 9
b10000000000000 7
b11111111 L
b1 :
b1000000000000 <
b0 I
b10000000000000 >
b10111101000010000000011111100000 R
b11111101010111101000111011100101011110110000010000001110111000001011110100001000000001111110000011111011001011110001110111100101 ,
b11111101010111101000111011100101011110110000010000001110111000001011110100001000000001111110000011111011001011110001110111100101 Y
b1111011000001000000111011100000 S
b100000000000 ?
b100000000000 C
b100000000000 P
b1100000000000 B
b1100000000000 O
b10000000000000001000000000000000000000111111110001000000000000 +
b10000000000000001000000000000000000000111111110001000000000000 8
b11111111 =
b11111111 A
b11111111 N
b10000011111111 @
b10000011111111 M
b11011101000010001110111000011111 X
b11011101000010001110111000011111 a
b10111011000001001101110100011111 W
b10111011000001001101110100011111 e
b100000000000 D
b1100011111111 E
b0 F
b10000000000000 G
b11101110100000000111011100011111 ^
b11101110100000000111011100011111 b
b10000000000000000000000000000000011000111111110000100000000000 .
b10000000000000000000000000000000011000111111110000100000000000 3
b100000000000000000000000000000 1
b100000000000000000000000000000 5
b100000000000000000000000000000 H
b100000000000000000000000000000 U
b100000000000000000000000000000 _
b100000000000000000000000000000 c
b100000000000000000000000000000 g
1$
#50000
0$
#55000
b11010011000001011100101011111010 V
b11010011000001011100101011111010 `
b11010011000001011100101011111010 d
b11010011000001011100101011111010 h
b11000110000011000000100100000000 Q
b11000110000011000000100100000000 f
b10111101000010000000011111100000111110110010111100011101111001011111110101011110100011101110010101111011000001000000111011100000 !
b10111101000010000000011111100000111110110010111100011101111001011111110101011110100011101110010101111011000001000000111011100000 -
b11111101010111101000111011100101 ]
b1111011000001000000111011100000 \
b10111101000010000000011111100000 [
b11111011001011110001110111100101 Z
b11111101010111101000111011100101011110110000010000001110111000001011110100001000000001111110000011111011001011110001110111100101 /
b11111101010111101000111011100101011110110000010000001110111000001011110100001000000001111110000011111011001011110001110111100101 T
b110 0
b110 4
b10000000000000 7
b100 9
b10 :
b0 >
b10000011000011100101101100011111 R
b10111101000010000000011111100000000001110000011110110110000111111000001100001110010110110001111101111011000001000000111011100000 ,
b10111101000010000000011111100000000001110000011110110110000111111000001100001110010110110001111101111011000001000000111011100000 Y
b111000001111011011000011111 S
b1000000000000 ?
b1000000000000 C
b1000000000000 P
b0 B
b0 O
b10000000000000000000000000000000100000111111110001000000000000 +
b10000000000000000000000000000000100000111111110001000000000000 8
b10000011111111 =
b10000011111111 A
b10000011111111 N
b1111110010100001101010111111010 X
b1111110010100001101010111111010 a
b11111100001010001010101111111010 W
b11111100001010001010101111111010 e
b1000000000000 D
b11111111 E
b10000000000000 F
b11110011000001011110101011111010 ^
b11110011000001011110101011111010 b
b10000000000000001000000000000000000000111111110001000000000000 .
b10000000000000001000000000000000000000111111110001000000000000 3
b100000000000000010000000000000 1
b100000000000000010000000000000 5
b100000000000000010000000000000 H
b100000000000000010000000000000 U
b100000000000000010000000000000 _
b100000000000000010000000000000 c
b100000000000000010000000000000 g
1$
#60000
0$
#65000
b11110110011000001000110110011111 V
b11110110011000001000110110011111 `
b11110110011000001000110110011111 d
b11110110011000001000110110011111 h
b10000100000010011110110100000000 Q
b10000100000010011110110100000000 f
b10100000000000 7
b101 9
b10000011000011100101101100011111011110110000010000001110111000001011110100001000000001111110000000000111000001111011011000011111 !
b10000011000011100101101100011111011110110000010000001110111000001011110100001000000001111110000000000111000001111011011000011111 -
b10111101000010000000011111100000 ]
b111000001111011011000011111 \
b10000011000011100101101100011111 [
b1111011000001000000111011100000 Z
b10111101000010000000011111100000000001110000011110110110000111111000001100001110010110110001111101111011000001000000111011100000 /
b10111101000010000000011111100000000001110000011110110110000111111000001100001110010110110001111101111011000001000000111011100000 T
b111 0
b111 4
b11000000000000 <
b10000000000000 >
b1100111000011100001110001111111 R
b10000011000011100101101100011111110011100000011100111000011111110110011100001110000111000111111100000111000001111011011000011111 ,
b10000011000011100101101100011111110011100000011100111000011111110110011100001110000111000111111100000111000001111011011000011111 Y
b11001110000001110011100001111111 S
b10000000000000 B
b10000000000000 O
b10100000000000001000000000000000000000111111110011000000000000 +
b10100000000000001000000000000000000000111111110011000000000000 8
b11111111 =
b11111111 A
b11111111 N
b11011010000001100001101110011111 X
b11011010000001100001101110011111 a
b10110101000000110011011010011111 W
b10110101000000110011011010011111 e
b10000011111111 E
b0 F
b11010110011000001000110110011111 ^
b11010110011000001000110110011111 b
b10000000000000000000000000000000100000111111110001000000000000 .
b10000000000000000000000000000000100000111111110001000000000000 3
b100000000000000000000000000000 1
b100000000000000000000000000000 5
b100000000000000000000000000000 H
b100000000000000000000000000000 U
b100000000000000000000000000000 _
b100000000000000000000000000000 c
b100000000000000000000000000000 g
1$
#70000
0$
#75000
b11110110000011011010000011110010 V
b11110110000011011010000011110010 `
b11110110000011011010000011110010 d
b11110110000011011010000011110010 h
b10101001000010010010010000000000 Q
b10101001000010010010010000000000 f
b1100111000011100001110001111111000001110000011110110110000111111000001100001110010110110001111111001110000001110011100001111111 !
b1100111000011100001110001111111000001110000011110110110000111111000001100001110010110110001111111001110000001110011100001111111 -
b10000011000011100101101100011111 ]
b11001110000001110011100001111111 \
b1100111000011100001110001111111 [
b111000001111011011000011111 Z
b10000011000011100101101100011111110011100000011100111000011111110110011100001110000111000111111100000111000001111011011000011111 /
b10000011000011100101101100011111110011100000011100111000011111110110011100001110000111000111111100000111000001111011011000011111 T
b1000 0
b1000 4
b111000000000000 7
b1110 9
b110 :
b100000000000 >
b1011000110111100101101011101101 R
b1100111000011100001110001111111101100000110111110110100111011010101100011011110010110101110110111001110000001110011100001111111 ,
b1100111000011100001110001111111101100000110111110110100111011010101100011011110010110101110110111001110000001110011100001111111 Y
b10110000011011111011010011101101 S
b11000000000000 ?
b11000000000000 C
b11000000000000 P
b0 B
b0 O
b111000000000000000010000000000000100000111111110011000000000000 +
b111000000000000000010000000000000100000111111110011000000000000 8
b10000011111111 =
b10000011111111 A
b10000011111111 N
b10100011111111 @
b10100011111111 M
b11011011110100000000000111110010 X
b11011011110100000000000111110010 a
b10110111011010000000001011110010 W
b10110111011010000000001011110010 e
b11000000000000 D
b11111111 E
b10000000000000 F
b10100000000000 G
b11011110000011011000000011110010 ^
b11011110000011011000000011110010 b
b10100000000000001000000000000000000000111111110011000000000000 .
b10100000000000001000000000000000000000111111110011000000000000 3
b101000000000000010000000000000 1
b101000000000000010000000000000 5
b101000000000000010000000000000 H
b101000000000000010000000000000 U
b101000000000000010000000000000 _
b101000000000000010000000000000 c
b101000000000000010000000000000 g
1$
#80000
0$
